CHANGES.rst
LICENSE.txt
MANIFEST.in
README.rst
output.txt
requirements.txt
setup.py
spexcript_spec.txt
testspex.txt
todo.txt
spexcript/__init__.py
spexcript/__main__.py
spexcript/base.py
spexcript/language.py
spexcript/latex.py
spexcript/layout.py
spexcript/text.py
spexcript.egg-info/.dropbox.attr
spexcript.egg-info/PKG-INFO
spexcript.egg-info/SOURCES.txt
spexcript.egg-info/dependency_links.txt
spexcript.egg-info/requires.txt
spexcript.egg-info/top_level.txt