Metadata-Version: 1.1
Name: spexcript
Version: 0.3
Summary: Spexcript -- easy layout for theater scripts
Home-page: https://github.com/k7hoven/spexcript
Author: Koos Zevenhoven
Author-email: koos.zevenhoven@aalto.fi
License: BSD
Platform: UNKNOWN
Classifier: Development Status :: 4 - Beta
Classifier: Natural Language :: English
Classifier: Operating System :: OS Independent
Classifier: Programming Language :: Python :: 3
